[
  {
    "username": "Ritalin06",
    "date": "27 Temmuz 2025 19:52:07",
    "page": 1,
    "otel": "Ali Bey Resort Sorgun",
    "fiyat": "gecelik 70 bin TL",
    "ozet": "İçecekler kötü ama deniz ve plaj çok temiz, fiyat/performans iyi.",
    "mesaj": "(ÖRNEK VERİ) Ali Bey Resort Sorgun'da kaldık, gecelik 70 bin TL civarıydı. İçkiler kötüydü ama deniz ve plaj tertemizdi, genel olarak fiyatına göre iyiydi."
  },
  {
    "username": "-PoseidoN-",
    "date": "27 Temmuz 2025 21:34:41",
    "page": 1,
    "otel": "Rixos Premium Belek",
    "fiyat": "kişi başı 4.500 EUR / hafta",
    "ozet": "Hizmet kusursuz ama fiyatlar bu sene aşırı arttı.",
    "mesaj": "(ÖRNEK VERİ) Rixos Premium Belek'te hizmet kusursuzdu fakat haftalık kişi başı 4.500 EUR fiyat bence fahiş, geçen seneye göre uçmuş."
  },
  {
    "username": "tatilci_42",
    "date": "28 Temmuz 2025 09:12:03",
    "page": 1,
    "otel": "Maxx Royal Kemer",
    "fiyat": null,
    "ozet": "Yemekler çok beğenildi, fiyat paylaşılmamış.",
    "mesaj": "(ÖRNEK VERİ) Maxx Royal Kemer'in yemekleri efsaneydi, a la carte restoranları özellikle çok iyi. Fiyatı paylaşmıyorum ama memnun kaldık."
  },
  {
    "username": "gezgin_07",
    "date": "28 Temmuz 2025 15:40:18",
    "page": 1,
    "otel": null,
    "fiyat": null,
    "ozet": "Genel bir teşekkür mesajı, otel veya fiyat bilgisi içermiyor.",
    "mesaj": "(ÖRNEK VERİ) Eline sağlık güzel konu olmuş, takipteyim. Herkese iyi tatiller."
  }
]
